cubicweb_relationwidget/__init__.py
cubicweb_relationwidget/__pkginfo__.py
cubicweb_relationwidget/site_cubicweb.py
cubicweb_relationwidget/views.py
cubicweb_relationwidget/data/cubicweb_relationwidget.css
cubicweb_relationwidget/data/cubicweb_relationwidget.js
cubicweb_relationwidget/i18n/en.po
cubicweb_relationwidget/i18n/es.po
cubicweb_relationwidget/i18n/fr.po
cubicweb_relationwidget-0.10.0.dist-info/METADATA
cubicweb_relationwidget-0.10.0.dist-info/WHEEL
cubicweb_relationwidget-0.10.0.dist-info/entry_points.txt
cubicweb_relationwidget-0.10.0.dist-info/top_level.txt
cubicweb_relationwidget-0.10.0.dist-info/RECORD
