Metadata-Version: 2.1
Name: cubicweb-relationwidget
Version: 0.10.0
Summary: Provide a generic and ergonomic relation widget
Home-page: https://forge.extranet.logilab.fr/cubicweb/cubes/cubicweb-relationwidget
Author: LOGILAB S.A. (Paris, FRANCE)
Author-email: contact@logilab.fr
License: LGPL
Classifier: Environment :: Web Environment
Classifier: Framework :: CubicWeb
Classifier: Programming Language :: Python
Classifier: Programming Language :: JavaScript
Requires-Dist: cubicweb[postgresql] <5.0,>=4.0.0
Requires-Dist: cubicweb-bootstrap <3.0.0,>=2.0.0
Requires-Dist: cwtags >=1.2.3
